i2a_chat_api_client/__init__.py
i2a_chat_api_client/client.py
i2a_chat_api_client/exceptions.py
i2a_chat_api_client-1.3.1.dist-info/LICENSE.txt
i2a_chat_api_client-1.3.1.dist-info/METADATA
i2a_chat_api_client-1.3.1.dist-info/WHEEL
i2a_chat_api_client-1.3.1.dist-info/top_level.txt
i2a_chat_api_client-1.3.1.dist-info/RECORD
