Metadata-Version: 2.1
Name: i2a-chat-api-client
Version: 1.3.1
Summary: Sdk for i2a chat api
Download-URL: https://pypi.org/project/i2a_chat_api_client/
Author: i2a Solutions Inc.
Author-email: msyta@i2asolutions.com
License: MIT
Keywords: I2A Chat Api Client,I2A Chat Api,I2A Chat,Python 3,I2A Chat Api SDK
License-File: LICENSE.txt
Requires-Dist: requests (>=2.26.0)
